temp_sms/__init__.py
temp_sms-1.0.dist-info/LICENSE
temp_sms-1.0.dist-info/METADATA
temp_sms-1.0.dist-info/WHEEL
temp_sms-1.0.dist-info/top_level.txt
temp_sms-1.0.dist-info/RECORD
