Metadata-Version: 2.1
Name: temp_sms
Version: 1.0
Summary: Temporary phone numbers for receiving SMS in python.
Author: Commenter123321
License: GPL-3.0
Keywords: temporary,sms,number,python,phone,receive
License-File: LICENSE
Requires-Dist: playwright
